CHANGES.txt
DEPENDENCES.txt
README.txt
setup.py
src/__init__.py
src/ng/__init__.py
src/ng.app.link.egg-info/PKG-INFO
src/ng.app.link.egg-info/SOURCES.txt
src/ng.app.link.egg-info/dependency_links.txt
src/ng.app.link.egg-info/namespace_packages.txt
src/ng.app.link.egg-info/not-zip-safe
src/ng.app.link.egg-info/requires.txt
src/ng.app.link.egg-info/top_level.txt
src/ng/app/__init__.py
src/ng/app/link/__init__.py
src/ng/app/link/configure.zcml
src/ng/app/link/interfaces.py
src/ng/app/link/link.py
src/ng/app/link/browser/__init__.py
src/ng/app/link/browser/configure.zcml
src/ng/app/link/etc/ng.app.link-configure.zcml
src/ng/app/link/link2obadapter/__init__.py
src/ng/app/link/link2obadapter/configure.zcml
src/ng/app/link/link2obadapter/link2obadapter.py
src/ng/app/link/linkbackreference/__init__.py
src/ng/app/link/linkbackreference/configure.zcml
src/ng/app/link/linkbackreference/interfaces.py
src/ng/app/link/linkbackreference/linkbackreference.py
src/ng/app/link/linkbackreference/linkbackreferenceitems.py
src/ng/app/link/linkbackreference/browser/__init__.py
src/ng/app/link/linkbackreference/browser/configure.zcml
src/ng/app/link/linkhandler/__init__.py
src/ng/app/link/linkhandler/configure.zcml
src/ng/app/link/linkhandler/linkhandler.py
src/ng/app/link/obhandler/__init__.py
src/ng/app/link/obhandler/configure.zcml
src/ng/app/link/obhandler/obhandler.py
